conan_mcp/__init__.py
conan_mcp/main.py
conan_mcp-0.1.0.dist-info/licenses/LICENSE
test/__init__.py
test/test_tools_audit.py
test/test_tools_check_licenses.py
test/test_tools_create_conan_project.py
test/test_tools_install.py
test/test_tools_list.py
test/test_tools_profiles.py
conan_mcp-0.1.0.dist-info/METADATA
conan_mcp-0.1.0.dist-info/WHEEL
conan_mcp-0.1.0.dist-info/entry_points.txt
conan_mcp-0.1.0.dist-info/top_level.txt
conan_mcp-0.1.0.dist-info/RECORD
