Metadata-Version: 2.4
Name: conan-mcp
Version: 0.1.0
Summary: MCP server for Conan package manager
License: The MIT License (MIT)
Project-URL: Homepage, https://github.com/conan-io/conan-mcp
Project-URL: Repository, https://github.com/conan-io/conan-mcp
Project-URL: Issues, https://github.com/conan-io/conan-mcp/issues
Requires-Python: >=3.10
License-File: LICENSE
Requires-Dist: conan>=2.22.1
Requires-Dist: mcp[cli]>=1.16.0
Requires-Dist: pydantic>=2.0.0
Provides-Extra: test
Requires-Dist: pytest>=7.0.0; extra == "test"
Dynamic: license-file
